stracetools/__init__.py
stracetools/analyzer.py
stracetools/parser.py
stracetools/visualizer.py
stracetools/data/default_syscall_colors.json
stracetools-1.0.0.dist-info/licenses/LICENSE
stracetools-1.0.0.dist-info/METADATA
stracetools-1.0.0.dist-info/WHEEL
stracetools-1.0.0.dist-info/top_level.txt
stracetools-1.0.0.dist-info/RECORD
